LICENSE
README.md
setup.cfg
setup.py
wwpdb/__init__.py
wwpdb.apps.content_ws_server.egg-info/PKG-INFO
wwpdb.apps.content_ws_server.egg-info/SOURCES.txt
wwpdb.apps.content_ws_server.egg-info/dependency_links.txt
wwpdb.apps.content_ws_server.egg-info/not-zip-safe
wwpdb.apps.content_ws_server.egg-info/requires.txt
wwpdb.apps.content_ws_server.egg-info/top_level.txt
wwpdb/apps/__init__.py
wwpdb/apps/content_ws_server/__init__.py
wwpdb/apps/content_ws_server/content/ContentRequest.py
wwpdb/apps/content_ws_server/content/ContentRequestPolicyFilter.py
wwpdb/apps/content_ws_server/content/ContentRequestProxyReportPdbx.py
wwpdb/apps/content_ws_server/content/ContentRequestReportDb.py
wwpdb/apps/content_ws_server/content/ContentRequestReportIo.py
wwpdb/apps/content_ws_server/content/ContentRequestReportPdbx.py
wwpdb/apps/content_ws_server/content/__init__.py
wwpdb/apps/content_ws_server/content_definitions/ContentDefintions.py
wwpdb/apps/content_ws_server/content_definitions/__init__.py
wwpdb/apps/content_ws_server/content_definitions/ws_content_type_definitions.json
wwpdb/apps/content_ws_server/message_queue/MessageQueue.py
wwpdb/apps/content_ws_server/message_queue/__init__.py
wwpdb/apps/content_ws_server/register/Register.py
wwpdb/apps/content_ws_server/register/__init__.py
wwpdb/apps/content_ws_server/service/ContentRequestServiceHandler.py
wwpdb/apps/content_ws_server/service/__init__.py
wwpdb/apps/content_ws_server/webapp/ContentServiceAppWorker.py
wwpdb/apps/content_ws_server/webapp/WebServiceApp.py
wwpdb/apps/content_ws_server/webapp/__init__.py
wwpdb/apps/content_ws_server/webapp/wsgi.py