Metadata-Version: 2.1
Name: wwpdb.apps.content-ws-server
Version: 0.8.dev1
Summary: wwPDB remote Content WS server
Home-page: https://github.com/wwPDB/py-wwpdb_apps_content_ws_server
Author: Ezra Peisach
Author-email: ezra.peisach@rcsb.org
License: Apache 2.0
Classifier: Development Status :: 3 - Alpha
Classifier: Intended Audience :: Developers
Classifier: Natural Language :: English
Classifier: License :: OSI Approved :: Apache Software License
Classifier: Programming Language :: Python
Classifier: Programming Language :: Python :: 3
Classifier: Programming Language :: Python :: 3.6
Classifier: Programming Language :: Python :: 3.7
Requires-Python: >=3.4
Provides-Extra: dev
Provides-Extra: test
Provides-Extra: server
License-File: LICENSE
